upss/__init__.py
upss/applications.py
upss/client.py
upss/connection.py
upss/consts.py
upss/exception.py
upss/log.py
upss/models.py
upss/server.py
upss/utils.py
upss/security/__init__.py
upss/security/crypto.py
upss/security/cryptographer.py
upss_py-0.0.2.dist-info/licenses/LICENSE
upss_py-0.0.2.dist-info/METADATA
upss_py-0.0.2.dist-info/WHEEL
upss_py-0.0.2.dist-info/top_level.txt
upss_py-0.0.2.dist-info/RECORD
