Metadata-Version: 2.4
Name: upss-py
Version: 0.0.2
Summary: Library for UPSS
Author: kosinak
Author-email: dargas020@gmail.com
License: MIT-License
Project-URL: GitHub, https://github.com/Dargas020/upss-python
Keywords: upss protocol
Classifier: Programming Language :: Python :: 3.12
Classifier: Operating System :: OS Independent
Requires-Python: >=3.9
License-File: LICENSE
Requires-Dist: cryptography>=46.0.3
Dynamic: author
Dynamic: author-email
Dynamic: classifier
Dynamic: description
Dynamic: description-content-type
Dynamic: keywords
Dynamic: license
Dynamic: license-file
Dynamic: project-url
Dynamic: requires-dist
Dynamic: requires-python
Dynamic: summary
